odoo/addons/shopinvader_address/README.rst
odoo/addons/shopinvader_address/__init__.py
odoo/addons/shopinvader_address/__manifest__.py
odoo/addons/shopinvader_address/i18n/shopinvader_address.pot
odoo/addons/shopinvader_address/models/__init__.py
odoo/addons/shopinvader_address/models/res_partner.py
odoo/addons/shopinvader_address/readme/CONTRIBUTORS.rst
odoo/addons/shopinvader_address/readme/DESCRIPTION.rst
odoo/addons/shopinvader_address/readme/USAGE.rst
odoo/addons/shopinvader_address/static/description/index.html
odoo_addon_shopinvader_address-16.0.1.1.1.dist-info/METADATA
odoo_addon_shopinvader_address-16.0.1.1.1.dist-info/WHEEL
odoo_addon_shopinvader_address-16.0.1.1.1.dist-info/top_level.txt
odoo_addon_shopinvader_address-16.0.1.1.1.dist-info/RECORD
